{
  "paragraphs": [
    {
      "text": "%dep\nz.reset()\n//z.load(\"org.apache.spark:spark-streaming-twitter_2.11:1.5.2\")\nz.load(\"org.apache.bahir:spark-streaming-twitter_2.11:2.0.1\")\nz.load(\"org.twitter4j:twitter4j-core:3.0.3\")\nz.load(\"org.twitter4j:twitter4j-media-support:3.0.3\")\nz.load(\"org.twitter4j:twitter4j-async:3.0.3\")\nz.load(\"org.twitter4j:twitter4j-examples:3.0.3\")\nz.load(\"org.twitter4j:twitter4j-stream:3.0.3\")\n",
      "user": "anonymous",
      "dateUpdated": "Sep 14, 2017 4:43:44 PM",
      "config": {
        "colWidth": 12.0,
        "enabled": true,
        "results": {},
        "editorSetting": {
          "language": "text",
          "editOnDblClick": false
        },
        "editorMode": "ace/mode/text"
      },
      "settings": {
        "params": {},
        "forms": {}
      },
      "results": {
        "code": "SUCCESS",
        "msg": [
          {
            "type": "TEXT",
            "data": "res0: org.apache.zeppelin.dep.Dependency \u003d org.apache.zeppelin.dep.Dependency@fed2c9\n"
          }
        ]
      },
      "apps": [],
      "jobName": "paragraph_1505351626339_2072182766",
      "id": "20170914-011346_36115199",
      "dateCreated": "Sep 14, 2017 1:13:46 AM",
      "dateStarted": "Sep 14, 2017 4:43:44 PM",
      "dateFinished": "Sep 14, 2017 4:43:48 PM",
      "status": "FINISHED",
      "progressUpdateIntervalMs": 500
    },
    {
      "text": "%spark\nimport org.apache.spark.streaming._\nimport org.apache.spark.streaming.twitter._\n//import org.apache.bahir.spark.streaming.twitter._\nimport org.apache.spark.storage.StorageLevel\nimport scala.io.Source\nimport scala.collection.mutable.HashMap\nimport java.io.File\nimport org.apache.log4j.Logger\nimport org.apache.log4j.Level\nimport sys.process.stringSeqToProcess\nimport twitter4j.HashtagEntity\n\nval consumerKey \u003d System.getenv(\"TWITTER_CONSUMER_KEY\")\nval consumerSecret \u003d System.getenv(\"TWITTER_CONSUMER_SECRET\")\nval accessToken \u003d System.getenv(\"TWITTER_ACCESS_TOKEN\")\nval accessTokenSecret \u003d System.getenv(\"TWITTER_ACCESS_SECRET\")\n\nSystem.setProperty(\"twitter4j.oauth.consumerKey\", consumerKey)\nSystem.setProperty(\"twitter4j.oauth.consumerSecret\", consumerSecret)\nSystem.setProperty(\"twitter4j.oauth.accessToken\", accessToken)\nSystem.setProperty(\"twitter4j.oauth.accessTokenSecret\", accessTokenSecret)\n\n\n",
      "user": "anonymous",
      "dateUpdated": "Sep 14, 2017 4:43:56 PM",
      "config": {
        "colWidth": 12.0,
        "enabled": true,
        "results": {},
        "editorSetting": {
          "language": "text",
          "editOnDblClick": false
        },
        "editorMode": "ace/mode/text"
      },
      "settings": {
        "params": {},
        "forms": {}
      },
      "results": {
        "code": "SUCCESS",
        "msg": [
          {
            "type": "TEXT",
            "data": "\nimport org.apache.spark.streaming._\n\nimport org.apache.spark.streaming.twitter._\n\nimport org.apache.spark.storage.StorageLevel\n\nimport scala.io.Source\n\nimport scala.collection.mutable.HashMap\n\nimport java.io.File\n\nimport org.apache.log4j.Logger\n\nimport org.apache.log4j.Level\n\nimport sys.process.stringSeqToProcess\n\nimport twitter4j.HashtagEntity\n\nconsumerKey: String \u003d bcfMz9WsSeJLAFKs8DcSCq5qS\n\nconsumerSecret: String \u003d Cy33bYqk9JWUr3kvGqzaLnwbBfv3BLZ4M6nysxPpBMUUAu1JJE\n\naccessToken: String \u003d 4332384689-zNH8ikndg5Mq8icy07Kvni6TmP2zEg43L21Ftca\n\naccessTokenSecret: String \u003d Rz7ZvL05ywhxMvKyRaxhxAVUkjGrwHlug2fTvxRzhN3YW\n\nres3: String \u003d null\n\nres4: String \u003d null\n\nres5: String \u003d null\n\nres6: String \u003d null\n"
          }
        ]
      },
      "apps": [],
      "jobName": "paragraph_1505351755131_617214023",
      "id": "20170914-011555_1380296648",
      "dateCreated": "Sep 14, 2017 1:15:55 AM",
      "dateStarted": "Sep 14, 2017 4:43:56 PM",
      "dateFinished": "Sep 14, 2017 4:44:03 PM",
      "status": "FINISHED",
      "progressUpdateIntervalMs": 500
    },
    {
      "title": "https://spark.apache.org/docs/latest/streaming-programming-guide.html",
      "text": "%spark\nimport org.apache.spark.streaming.twitter._\nval ssc \u003d new StreamingContext(sc, Seconds(10))\nval tweets \u003d TwitterUtils.createStream(ssc, None, Array(\"#Irma\"))\n//val tweets \u003d TwitterUtils.createStream(ssc, None)\n//tweets.saveAsObjectFiles(\"hdfs://sandbox.hortonworks.com:8020/test/twitter-spark/twitter_\", \".txt\")\n\nval twt \u003d tweets.window(Seconds(120))\n\ncase class Tweet(createdAt:Long, text:String, screenName:String)\ntwt.map(t\u003d\u003e\n  Tweet(t.getCreatedAt().getTime()/1000, t.getText(), t.getUser().getScreenName())).foreachRDD(rdd\u003d\u003e{\n    rdd.toDF().registerTempTable(\"tweets\")\n}\n)\n\n//twt.print\n\nssc.start()\n",
      "user": "anonymous",
      "dateUpdated": "Sep 14, 2017 4:44:58 PM",
      "config": {
        "colWidth": 12.0,
        "enabled": true,
        "results": {},
        "editorSetting": {
          "language": "text",
          "editOnDblClick": false
        },
        "editorMode": "ace/mode/text",
        "title": true
      },
      "settings": {
        "params": {},
        "forms": {}
      },
      "results": {
        "code": "SUCCESS",
        "msg": [
          {
            "type": "TEXT",
            "data": "\nimport org.apache.spark.streaming.twitter._\n\nssc: org.apache.spark.streaming.StreamingContext \u003d org.apache.spark.streaming.StreamingContext@4581659\n\ntweets: org.apache.spark.streaming.dstream.ReceiverInputDStream[twitter4j.Status] \u003d org.apache.spark.streaming.twitter.TwitterInputDStream@4d6215b4\n\ntwt: org.apache.spark.streaming.dstream.DStream[twitter4j.Status] \u003d org.apache.spark.streaming.dstream.WindowedDStream@27c5a021\n\ndefined class Tweet\n\nwarning: there was one deprecation warning; re-run with -deprecation for details\n"
          }
        ]
      },
      "apps": [],
      "jobName": "paragraph_1505351812660_-1350499122",
      "id": "20170914-011652_1852008891",
      "dateCreated": "Sep 14, 2017 1:16:52 AM",
      "dateStarted": "Sep 14, 2017 4:44:58 PM",
      "dateFinished": "Sep 14, 2017 4:45:00 PM",
      "status": "FINISHED",
      "progressUpdateIntervalMs": 500
    },
    {
      "text": "%sql\n-- checking window contents\n\nselect from_unixtime(createdAt), count(1) from tweets group by createdAt order by createdAt\n",
      "user": "anonymous",
      "dateUpdated": "Sep 14, 2017 4:45:38 PM",
      "config": {
        "colWidth": 12.0,
        "enabled": true,
        "results": {
          "0": {
            "graph": {
              "mode": "table",
              "height": 300.0,
              "optionOpen": false,
              "setting": {
                "multiBarChart": {
                  "stacked": false
                },
                "pieChart": {}
              },
              "commonSetting": {},
              "keys": [],
              "groups": [],
              "values": [
                {
                  "name": "count(1)",
                  "index": 1.0,
                  "aggr": "sum"
                }
              ]
            },
            "helium": {}
          }
        },
        "editorSetting": {
          "language": "text",
          "editOnDblClick": false
        },
        "editorMode": "ace/mode/text"
      },
      "settings": {
        "params": {},
        "forms": {}
      },
      "results": {
        "code": "SUCCESS",
        "msg": [
          {
            "type": "TABLE",
            "data": "from_unixtime(createdAt, yyyy-MM-dd HH:mm:ss)\tcount(1)\n2017-09-14 16:45:00\t1\n2017-09-14 16:45:02\t1\n2017-09-14 16:45:03\t3\n2017-09-14 16:45:05\t1\n2017-09-14 16:45:08\t3\n2017-09-14 16:45:10\t4\n2017-09-14 16:45:11\t5\n2017-09-14 16:45:12\t1\n2017-09-14 16:45:14\t1\n2017-09-14 16:45:15\t1\n2017-09-14 16:45:16\t1\n2017-09-14 16:45:17\t3\n2017-09-14 16:45:18\t3\n2017-09-14 16:45:20\t5\n2017-09-14 16:45:21\t2\n2017-09-14 16:45:22\t1\n2017-09-14 16:45:23\t1\n2017-09-14 16:45:24\t3\n2017-09-14 16:45:25\t1\n2017-09-14 16:45:26\t4\n2017-09-14 16:45:27\t2\n2017-09-14 16:45:28\t4\n"
          }
        ]
      },
      "apps": [],
      "jobName": "paragraph_1505352092138_-754323861",
      "id": "20170914-012132_849022349",
      "dateCreated": "Sep 14, 2017 1:21:32 AM",
      "dateStarted": "Sep 14, 2017 4:45:38 PM",
      "dateFinished": "Sep 14, 2017 4:45:38 PM",
      "status": "FINISHED",
      "progressUpdateIntervalMs": 500
    },
    {
      "text": "/* declaring a function in Scala */\n\ndef sentiment(s:String) : String \u003d {\n    val positive \u003d Array(\"like\", \"love\", \"good\", \"great\", \"happy\", \"cool\", \"the\", \"one\", \"that\")\n    val negative \u003d Array(\"hate\", \"bad\", \"stupid\", \"is\")\n\n    var st \u003d 0;\n\n    val words \u003d s.split(\" \")    \n    positive.foreach(p \u003d\u003e\n        words.foreach(w \u003d\u003e\n            if(p\u003d\u003dw) st \u003d st+1\n        )\n    )\n\n    negative.foreach(p\u003d\u003e\n        words.foreach(w\u003d\u003e\n            if(p\u003d\u003dw) st \u003d st-1\n        )\n    )\n    if(st\u003e0)\n        \"positivie\"\n    else if(st\u003c0)\n        \"negative\"\n    else\n        \"neutral\"\n}\n\nsqlc.udf.register(\"sentiment\", sentiment _)\n",
      "user": "anonymous",
      "dateUpdated": "Sep 14, 2017 4:46:22 PM",
      "config": {
        "colWidth": 12.0,
        "enabled": true,
        "results": {},
        "editorSetting": {
          "language": "text",
          "editOnDblClick": false
        },
        "editorMode": "ace/mode/text"
      },
      "settings": {
        "params": {},
        "forms": {}
      },
      "results": {
        "code": "SUCCESS",
        "msg": [
          {
            "type": "TEXT",
            "data": "\nsentiment: (s: String)String\n\nres19: org.apache.spark.sql.expressions.UserDefinedFunction \u003d UserDefinedFunction(\u003cfunction1\u003e,StringType,Some(List(StringType)))\n"
          }
        ]
      },
      "apps": [],
      "jobName": "paragraph_1505352108026_159100676",
      "id": "20170914-012148_1747510058",
      "dateCreated": "Sep 14, 2017 1:21:48 AM",
      "dateStarted": "Sep 14, 2017 4:46:22 PM",
      "dateFinished": "Sep 14, 2017 4:46:23 PM",
      "status": "FINISHED",
      "progressUpdateIntervalMs": 500
    },
    {
      "text": "%pyspark\n\n#declaring a function in Python\n\nimport re\n\ndef wordcount(a):\n  return len(re.split(\"\\W+\",a))\n  \nsqlContext.registerFunction(\"wordcount\", wordcount)\n",
      "user": "anonymous",
      "dateUpdated": "Sep 14, 2017 4:46:51 PM",
      "config": {
        "colWidth": 12.0,
        "enabled": true,
        "results": {},
        "editorSetting": {
          "language": "text",
          "editOnDblClick": false
        },
        "editorMode": "ace/mode/text"
      },
      "settings": {
        "params": {},
        "forms": {}
      },
      "results": {
        "code": "SUCCESS",
        "msg": []
      },
      "apps": [],
      "jobName": "paragraph_1505352139936_555822764",
      "id": "20170914-012219_747991536",
      "dateCreated": "Sep 14, 2017 1:22:19 AM",
      "dateStarted": "Sep 14, 2017 4:46:51 PM",
      "dateFinished": "Sep 14, 2017 4:46:52 PM",
      "status": "FINISHED",
      "progressUpdateIntervalMs": 500
    },
    {
      "text": "%sql\n\n--using SQL to mix window data, with scala function and python function\n\nselect from_unixtime(createdAt) as created, screenName, sentiment(text) as sentiment, wordcount(text) as wordcount, text  from tweets\n\n",
      "user": "anonymous",
      "dateUpdated": "Sep 14, 2017 4:48:37 PM",
      "config": {
        "colWidth": 12.0,
        "enabled": true,
        "results": {
          "0": {
            "graph": {
              "mode": "pieChart",
              "height": 300.0,
              "optionOpen": true,
              "setting": {
                "scatterChart": {
                  "xAxis": {
                    "name": "wordcount",
                    "index": 3.0,
                    "aggr": "sum"
                  },
                  "yAxis": {
                    "name": "sentiment",
                    "index": 2.0,
                    "aggr": "sum"
                  }
                },
                "multiBarChart": {
                  "stacked": false
                }
              },
              "commonSetting": {},
              "keys": [
                {
                  "name": "screenName",
                  "index": 1.0,
                  "aggr": "sum"
                }
              ],
              "groups": [
                {
                  "name": "sentiment",
                  "index": 2.0,
                  "aggr": "sum"
                }
              ],
              "values": [
                {
                  "name": "wordcount",
                  "index": 3.0,
                  "aggr": "sum"
                }
              ]
            },
            "helium": {}
          }
        },
        "editorSetting": {
          "language": "text",
          "editOnDblClick": false
        },
        "editorMode": "ace/mode/text"
      },
      "settings": {
        "params": {},
        "forms": {}
      },
      "results": {
        "code": "SUCCESS",
        "msg": [
          {
            "type": "TABLE",
            "data": "created\tscreenName\tsentiment\twordcount\ttext\n2017-09-14 16:45:20\tRuffusMD\tneutral\t20\tRT @channel1atlanta: NEWS12-NBC26 reports RT BrookeWRDW: columbiactyga crews cleaning up debris left behind from #Irma WRDW_WAGT https://t.…\n2017-09-14 16:45:20\tConsumerFed\tneutral\t23\tAfter #Harvey and #Irma, there could be millions of flood damaged vehicles. Here\u0027s how to avoid buying one:… https://t.co/4NpwebN626\n2017-09-14 16:45:20\tRichDenee\tneutral\t15\tMaking sure our Dunnellon police dept feel our appreciation!\n#Irma \n#ThankfulForThem https://t.co/IywMgKPcjq\n2017-09-14 16:45:20\tJasonVarnum\tneutral\t15\tMaking sure our Dunnellon police dept feel our appreciation!\n#Irma \n#ThankfulForThem https://t.co/phfqtWIscm\n2017-09-14 16:45:21\tSherburnDeandr1\tneutral\t22\tRT @ConsumerFed: After #Harvey and #Irma, there could be millions of flood damaged vehicles. Here\u0027s how to avoid buying one:… \n2017-09-14 16:45:21\tOnCuba\tneutral\t20\t#Irma provocó daños a 211 instituciones culturales en #Cuba. https://t.co/af4aCkl9Gz #SociedadOnCuba https://t.co/GZ536t2wTi\n2017-09-14 16:45:20\tSHFPC\tneutral\t15\tMaking sure our Dunnellon police dept feel our appreciation!\n#Irma \n#ThankfulForThem https://t.co/xvd4dwYicl\n2017-09-14 16:45:22\tFlennerRandolph\tneutral\t21\tRT @OnCuba: #Irma provocó daños a 211 instituciones culturales en #Cuba. https://t.co/af4aCkl9Gz #SociedadOnCuba https://t.co/GZ536t2wTi\n2017-09-14 16:45:23\tJeremy_CRF\tneutral\t20\tRT @franceinfo: #Irma \"La première difficulté, elle est logistique, comment acheminer les équipes à Saint Martin\" Florent Vallée,… \n2017-09-14 16:45:24\tFatyCepeda\tneutral\t16\tRT @Hannasuewilson: There\u0027s a special place in heaven for this man https://t.co/AbGTdjzAHH\n2017-09-14 16:45:24\tCassiWinch\tneutral\t16\tRT @Hannasuewilson: There\u0027s a special place in heaven for this man https://t.co/AbGTdjzAHH\n2017-09-14 16:45:24\tjohnwdavis\tneutral\t23\tRT @MyNews13: Do you know of any children who need food during #Irma recovery? @OCPS_FNS is distrusting food today at the followi… \n2017-09-14 16:45:25\tepappacoda\tnegative\t25\tMy fridge: before and after #Irma. All that\u0027s left is hot sauce, wine and a fresh can of dog food. https://t.co/C6tVuCsbrH\n2017-09-14 16:45:26\toblessa\tpositivie\t15\tRT @kellycutrone: Notice all the people shaking his hand are white https://t.co/BXE1MFLiLP\n2017-09-14 16:45:26\ttheflabar\tnegative\t15\tRT @expertsdotcomvp: Hotline is opened for #Hurricane #Irma related legal problems. https://t.co/nBggXPNPDP\n2017-09-14 16:45:26\tManders338\tpositivie\t20\tRT @jsosheriff: If you see anything that just doesn\u0027t look right, please call.....Great work!! https://t.co/0mjy9cHDKb\n2017-09-14 16:45:26\tJeremy_CRF\tneutral\t22\tRT @franceinfo: #Irma \"Nous avons ouvert très vite Family Links pour retrouver les personnes disparues\" Florent Vallée, Croix Rouge… \n2017-09-14 16:45:27\tRSIMartianos\tneutral\t12\t¡El último Tesoro de Cuba! https://t.co/YjwCKKGG7M #cuba #irma\n2017-09-14 16:45:27\tPedro_ACM\tneutral\t24\tRT @PrensaLatina_cu: “Médicos uruguayos graduados en #Cuba solidarios tras paso de huracán” https://t.co/OsREqClDVm #Irma https://t.co/mmTJ…\n2017-09-14 16:45:28\tanagsoncin\tneutral\t30\tRT @g1: Sobreviventes do Irma são resgatados de ilha e pousam no DF com avião da FAB https://t.co/ZaNQupRBNZ #Irma #G1 https://t.co/tojuhW5…\n2017-09-14 16:45:28\tjwchancey\tpositivie\t21\tRT @sanibelnik: Before #Irma this was the best burger on island....after, its still the #best. @lazyflamingo https://t.co/dSUSY6EsVG\n2017-09-14 16:45:28\tImSheezaVictor\tneutral\t15\t#irma #harvey #BernieSanders #Bernie2016 DECAL 5-PACK #FEELtheBERN  #CTL #BlackLivesMatter https://t.co/rcfQFNe4fB\n2017-09-14 16:45:28\tImHarmonyNewton\tneutral\t17\t#irma David Bowie Vinyl Decal WALL Sticker Anonymous #DavidBowie  #TopProg #DEMS #CTL https://t.co/mu5qsqNpCa\n2017-09-14 16:45:29\tJustisDA\tneutral\t9\t#POTUSinFlorida #FLOTUSinFlorida #VPinFlorida #Irma https://t.co/rXjPIui37G\n2017-09-14 16:45:29\tfahmidaaaaa_x\tneutral\t14\tRT @iHartDnB: G-R-E-N-F-E-L-L https://t.co/8Xt8dg8S5b\n2017-09-14 16:45:30\tGus_802\tneutral\t20\tRT @Carolyn_Cole: An exasperating hunt for gasoline in #Florida as #Hurricane #Irma\u0027s evacuees scramble to come home. #IrmaRecovery… \n2017-09-14 16:45:31\ttucsongirl1\tneutral\t24\tRT @CNNnewsroom: \"We\u0027ve been thrilled to have them\" - Millionaire Marc Bell opened $30m mansion to 70 foster kids displaced by #Irma https:…\n2017-09-14 16:45:32\titeachkidz\tneutral\t26\tRT @MDCPS: @MDCPS holds #Irma recovery food distribution events at 11:30 a.m. Additional sites added for 3 p.m. distribution. https://t.co/…\n2017-09-14 16:45:32\tjohnwdavis\tneutral\t28\tRT @MyNews13: FREE WATER IN PALM BAY: The city will give away cases of water to residents today at 1 p.m. at City Hall. 1st come,… \n2017-09-14 16:45:32\tBigBeacon\tpositivie\t24\tinfluencemags: Our #Summer Roadtrip was thrown a curve by #Irma but that meant new cities to explore! Watch for up… https://t.co/jKsYkFyiIG\n2017-09-14 16:45:33\tPrensaLatina_cu\tneutral\t16\tConsejo de Iglesias de #Cuba contribuirá en la recuperación tras #Irma https://t.co/blern9aBbZ\n2017-09-14 16:45:33\tAbArkle71\tneutral\t22\tRT @ABC: Kissimmee, Florida police officer dances with an elderly woman at a local emergency shelter to help ease her anxiet… \n2017-09-14 16:45:33\tploykm137\tneutral\t13\tRT @picturecats: Found this little nugget after Hurricane #Irma https://t.co/WQ3smPFcpo\n2017-09-14 16:45:34\tkikiblain_off\tneutral\t24\tRT @macronpiegeacon: Le grand pont aérien de #Macron du jamais vu. #Irma. Secouristes bloqués en #Guadeloupe😅 Quel rigolo, mon dieux !\nhttp…\n2017-09-14 16:45:35\tGeostompX\tneutral\t23\tRT @ABC: Sister Margaret Ann wields a chainsaw to help with #Irma clean-up effort at Archbishop Coleman Carroll HS in Miami.… \n2017-09-14 16:45:35\tdennerdenner\tpositivie\t17\tRT @quinncy: Yes, that\u0027s the horror of #Irma. Not enough dead people. https://t.co/rtAMoivjBl\n2017-09-14 16:45:36\tfab_zainz\tneutral\t14\tRT @iHartDnB: G-R-E-N-F-E-L-L https://t.co/8Xt8dg8S5b\n2017-09-14 16:45:36\tinejeunen\tneutral\t16\tRT @Hannasuewilson: There\u0027s a special place in heaven for this man https://t.co/AbGTdjzAHH\n2017-09-14 16:45:36\tsomeone_named\tneutral\t11\tRT @victoriaxo01: Well I wonder why Bryan https://t.co/eoZevA5Fll\n2017-09-14 16:45:36\tYourNews101\tpositivie\t24\tRT @YourNews101: VOTE and RETWEET, Did @POTUS Trump do a good job in dealing with and preparing for #Harvey and #Irma and with recovery\n2017-09-14 16:45:37\tfgonzalez1978\tneutral\t25\tRT @SaschaCordner: As of noon, more than 2.5 million homes, businesses still without power. Both FPL and Duke Energy each have 28% of… \n2017-09-14 16:45:38\tExoWARFARE\tpositivie\t22\tRT @USMC: Yesterday, Marines with the 26th MEU delivered over 52,000 pounds of relief supplies to victims of Hurricane #Irma,… \n2017-09-14 16:45:38\tgrayjustin\tpositivie\t23\tRT @BrandonANjax: It\u0027s great having @grayjustin at @ActionNewsJax to help with our Irma coverage! Much thanks! @COXMG https://t.co/VbIquOCO…\n2017-09-14 16:45:39\tanagsoncin\tneutral\t30\tRT @g1: Sobreviventes do Irma são resgatados de ilha e pousam no DF com avião da FAB https://t.co/ZaNQuq9cFx #Irma #G1 https://t.co/nP1XNKc…\n2017-09-14 16:45:39\tnoticiasmiled\tneutral\t22\t#Trump realiza visita a #Florida para constatar daños causados por #Irma @tvmiled https://t.co/0abKcFl8nZ https://t.co/9qBMQ0aiwf\n2017-09-14 16:45:39\tsalena_mabe\tneutral\t19\tRT @Knoxville_PD: Help us challenge @GainesvillePD by giving to your favorite charity for #Irma victims in Florida. #GoVols:… \n2017-09-14 16:45:41\tporshbby90\tneutral\t7\tRT @j_H22O: LMAOOOOOOOOOOO!!!!!! https://t.co/xQrSAFwjbs\n2017-09-14 16:45:41\tdolos_nova\tneutral\t17\tMe shooting my shot even when God giving me every sign to stop https://t.co/VVSsxl9tNS\n2017-09-14 16:45:42\tlopezgovlaw\tneutral\t16\tRT @SFLRedCross: Hurricane #Irma – One Volunteer’s Perspective: https://t.co/fYa22Cr35d https://t.co/NEc1unMtJc\n2017-09-14 16:45:43\tJoeGalaban\tneutral\t16\t#Cuba. #Irma, un coup très dur pour #LaHavane https://t.co/UzIxxRKSLw via @courrierinter\n2017-09-14 16:45:43\txandaolp\tneutral\t22\tRT @genejm29: NASA\u0027s #Terra satellite Observes Remnants of #Irma Ready to Exit Eastern United States | via #NASA https://t.co/m8ih9SvVdm\n2017-09-14 16:45:43\tsammybabes111\tpositivie\t12\tRT @Chloemeadows: This has made me so happy ❤️ https://t.co/JMVgtTcDUp\n2017-09-14 16:45:43\tCITYsidewalker\tneutral\t19\tRT @MiamiDadeCounty: #OurCounty continues to recover from #Irma. We are working tirelessly for our community. We are #MiamiDadeStrong.\n2017-09-14 16:45:44\t_emmaahorn\tneutral\t14\tRT @iHartDnB: G-R-E-N-F-E-L-L https://t.co/8Xt8dg8S5b\n2017-09-14 16:45:44\tCroes_Fam_Luv_3\tnegative\t12\tRT @gio_leocadia: This is a real heroe damn 😱🔥 https://t.co/q3ece9EWgN\n2017-09-14 16:45:44\tlucasmalabo15\tneutral\t14\tRT @NickKuk: This guys saving dogs!!! #hurricane #storm #miami #irma https://t.co/FreNqNXgFG\n2017-09-14 16:45:45\tMYLUCKYLIZZY\tneutral\t22\tRT @USArmy: .@USNationalGuard #Soldiers from more than 25 states area assisting with Hurricane #Irma relief efforts. #USArmy https://t.co/R…\n2017-09-14 16:45:46\tGrayzorback73\tneutral\t20\tRT @ABC: Pres. Trump and Vice Pres. Pence serve food to Florida residents impacted by Hurricane #Irma in Naples.… \n2017-09-14 16:45:47\tLalaannette143\tneutral\t22\tRT @USArmy: .@USNationalGuard #Soldiers from more than 25 states area assisting with Hurricane #Irma relief efforts. #USArmy https://t.co/R…\n2017-09-14 16:45:47\tJohnBoxer66\tneutral\t7\tRT @JohnBoxer66: #Priceless https://t.co/mtYDADWcgd\n2017-09-14 16:45:48\tTopmitch75\tpositivie\t22\tRT @USMC: Yesterday, Marines with the 26th MEU delivered over 52,000 pounds of relief supplies to victims of Hurricane #Irma,… \n2017-09-14 16:45:48\titarcusdo1986\tneutral\t9\tRT @americapl: #Irma en Cuba. https://t.co/fxeH1mzzLA\n2017-09-14 16:45:48\tsnoopsavine\tneutral\t16\tRT @Hannasuewilson: There\u0027s a special place in heaven for this man https://t.co/AbGTdjzAHH\n2017-09-14 16:45:49\tJustisDA\tneutral\t9\t#POTUSinFlorida #FLOTUSinFlorida #VPinFlorida #Irma https://t.co/HbmrS5z6P2\n2017-09-14 16:45:53\tcorinhoggard\tneutral\t20\tRT @ABCWorldNews: Pres. Trump and Vice Pres. Pence serve food to Florida residents impacted by Hurricane #Irma in Naples.… \n2017-09-14 16:45:53\tDakota_292\tneutral\t19\t@HarrisonFordLA Refilling my water supply as I have no water thanks to hurricane #Irma https://t.co/PFba6yCxmg\n2017-09-14 16:45:54\tlopezgovlaw\tneutral\t20\tRT @UniNoticias: Presidente Trump visitará Puerto Rico para ver las labores de recuperación por el huracán #Irma.… \n2017-09-14 16:45:54\tfbarrott36\tneutral\t17\tRT @WaffleHouseNews: @WaffleHouse Restaurants open and serving our customers in South Florida. #Irma https://t.co/CHVeczEGHn\n2017-09-14 16:45:55\tjamiechance05\tpositivie\t22\tRT @FordOConnell: It has to be killing the MSM how much Naples, FLA loves @realDonaldTrump as he meets with storm victims. #IRMA\n2017-09-14 16:45:56\tMinyawn\tneutral\t21\tRT @OnCuba: #Irma provocó daños a 211 instituciones culturales en #Cuba. https://t.co/af4aCkl9Gz #SociedadOnCuba https://t.co/GZ536t2wTi\n2017-09-14 16:45:56\tJamesforleader\tpositivie\t23\tRT @Number10gov: PM Theresa May has announced an additional £25m to support Hurricane #Irma recovery efforts, on top of the £32m announced…\n2017-09-14 16:45:56\tjasonlardy\tneutral\t10\tThe latest Nomad News! https://t.co/V6vG261JD4 #cpfc #irma\n2017-09-14 16:45:55\ttruckingguy23\tneutral\t12\tOur National Guard on 95 🇺🇸🇺🇸 #ThankOurTroops #Irma #Florida https://t.co/5tjm3DBfyO\n2017-09-14 16:45:56\tDiteaux\tneutral\t24\tRT @JewhadiTM: Street protests break out in Cuba on hurricane-ravaged streets of Havana over communist regime\u0027s #Irma failures https://t.co…\n2017-09-14 16:45:56\tsydneyxpage\tneutral\t16\tRT @Hannasuewilson: There\u0027s a special place in heaven for this man https://t.co/AbGTdjzAHH\n2017-09-14 16:45:58\tXRIM\tpositivie\t25\t#MONEY #IRMA WSJ\nHas the Bizarro Goldilocks economy reached the end of the fairy tale? https://t.co/KvGc5VCEP5\n— Wall Street Journal (WS…\n2017-09-14 16:45:58\tAntonioDoddi\tneutral\t23\tRT @Mowgli_Alg: Dites vous c\u0027 est un autre animal qui le sauve pendant que l\u0027humain il film mdr https://t.co/I11B4WaArj\n2017-09-14 16:45:59\tMaebeKen\tneutral\t16\tRT @Hannasuewilson: There\u0027s a special place in heaven for this man https://t.co/AbGTdjzAHH\n2017-09-14 16:46:00\tshannon21661\tneutral\t20\tRT @ABC: Pres. Trump and Vice Pres. Pence serve food to Florida residents impacted by Hurricane #Irma in Naples.… \n2017-09-14 16:46:00\tsexybadasslexxx\tneutral\t16\tRT @Hannasuewilson: There\u0027s a special place in heaven for this man https://t.co/AbGTdjzAHH\n2017-09-14 16:46:00\tIqbal704Javed\tneutral\t7\t@jeremycorbyn @ShellyAsquith https://t.co/KEtzN20HQA\n2017-09-14 16:46:00\twatermelo9100\tneutral\t15\tRT @Havenlust: Hurricane Irma giving gifts #Irma https://t.co/O0yoTavqQu https://t.co/1uScozSsTI\n2017-09-14 16:46:01\tpastor_bd\tpositivie\t17\tRT @quinncy: Yes, that\u0027s the horror of #Irma. Not enough dead people. https://t.co/rtAMoivjBl\n2017-09-14 16:46:01\tFocusOnMobility\tneutral\t15\t#mindfulness #growthmindset Surviving and Thriving in times of  #irma #harvey https://t.co/yElaTl8Tfz\n2017-09-14 16:46:02\tHish96\tneutral\t11\tRT @victoriaxo01: Well I wonder why Bryan https://t.co/eoZevA5Fll\n2017-09-14 16:46:03\tArquiman2\tneutral\t22\tRT @USEmbassyBogota: -@POTUS y @FLOTUS partieron hacia La Florida para reunirse con los afectados del huracán #Irma. https://t.co/elQ8F8ZcWF\n2017-09-14 16:46:04\tgregyeg\tneutral\t25\tRT @TNTContest: 🏆TNT-KO CONTEST🏆\nTweet (use 1/more):\n-Knock\n-Out\n-Hurricane\n-Boom\n3 max, ends 9/14, 9p est\nLast day to donate!… \n2017-09-14 16:46:03\tmannybiol\tneutral\t20\tRT @ricardorossello: We welcome in #PuertoRico hundreds stranded by #Irma in neighboring islands. Our authorities will receive you with… \n2017-09-14 16:46:04\tBobUSA47\tneutral\t25\tRT @GovMikeHuckabee: I love this! Service comes in big and small ways. This is a big way. God bless this officer! https://t.co/aM7l9ohg27\n2017-09-14 16:46:04\tyolenecrm\tneutral\t23\tRT @Mowgli_Alg: Dites vous c\u0027 est un autre animal qui le sauve pendant que l\u0027humain il film mdr https://t.co/I11B4WaArj\n2017-09-14 16:46:04\ttomCLanderson\tneutral\t14\tRT @iHartDnB: G-R-E-N-F-E-L-L https://t.co/8Xt8dg8S5b\n2017-09-14 16:46:04\tMomResource\tneutral\t16\tFantastic place to hide from #Irma \nhttps://t.co/cUFwnYJg0c @rossbridgehotel #RenHotels https://t.co/lW7oJA21XF\n2017-09-14 16:46:04\ttribilintoby\tnegative\t18\tRT @fema: The @USACEHQ is helping with generator installations, roofing, \u0026 debris removal after #Irma. More info here:… \n2017-09-14 16:46:05\tRoseKnudsen\tneutral\t19\tRT @ThisWeekABC: Pres. Trump and VP Pence serve food to Florida residents impacted by Hurricane #Irma in Naples.… \n2017-09-14 16:46:05\tjnl_j\tneutral\t23\tRT @JeanDuma1: Le Plus Grand Pont Aérien Du Monde...\n1 avion\n1 hélico\n1 mythomane\n#SaintMartin #Irma https://t.co/dAsMws1fTe\n2017-09-14 16:46:06\tDavis_404\tnegative\t22\tSomewhere is a previously bored \u0026 dismissive distributor of that needed part who is is nervously expecting a visit… https://t.co/78daBTxDJ7\n2017-09-14 16:46:06\tmay_APRIL_march\tnegative\t14\tRT @joonesiee: omfg i\u0027m crying he is so kind https://t.co/wA4wdkYoTb\n2017-09-14 16:46:06\tKbaneSylvie\tneutral\t26\tRT @Louisetre: \"En Guadeloupe, il y a des bâtiments publics qui ne sont pas aux normes parasismiques,à commencer par le CHU\" \nhttps://t.co/…\n2017-09-14 16:46:05\tM_Tresemer\tnegative\t20\tRT @PME_Sensors: What is influence of #climatechange in #Harvey and #Irma? Temperature plays clear, direct role, says @MichaelEMann https:/…\n2017-09-14 16:46:06\tJustisDA\tneutral\t9\t#POTUSinFlorida #FLOTUSinFlorida #VPinFlorida #Irma https://t.co/w7a9x2yrm3\n2017-09-14 16:46:06\tCoastal6524152\tneutral\t20\tCoastal Ocean Protection System shares with you interesting articles and information about our Oceans - NOAA fligh…… https://t.co/1mSXl74f03\n2017-09-14 16:46:08\tDakotaElec\tneutral\t23\tRT @NRECANews: Co-ops continue to make progress on #Irma outages. Power has been restored to nearly 75% of affected member-owners!… \n2017-09-14 16:46:09\tMiamiWeatherNow\tneutral\t22\tIt\u0027s 88F in #Miami with cloudy skies \u0026 winds at E 4.7mph #Irma https://t.co/KnD3jb1COv https://t.co/wPI9pI6Vb5\n2017-09-14 16:46:09\tChowjudy12\tneutral\t21\tRT @noaaocean: NOAA flight crew busy conducting overflights above areas affected by #Irma. Please continue to check for new images… \n2017-09-14 16:46:09\tRDelite\tnegative\t19\tRT @CityofSarasota: Robert L. Taylor Community Complex also is a location. Open today \u0026 tmrw @ 8 am. 😊👍 @RLTaylorComplex @HeraldTribune… \n2017-09-14 16:46:11\tTooglesEN\tneutral\t17\t👀 New knowledge about #Trump + #President + #Hurricane + #Florida + #Irma you\u0027ll find here 😉  https://t.co/mf4n6iSJcg\n2017-09-14 16:46:12\tFeedingNEFL\tneutral\t26\tWe are loading up a truck for our partner agency The Worship Center. They\u0027ll distribute at 10am Fri in northwest ja… https://t.co/7G7x7KIWXg\n2017-09-14 16:46:12\tBTW_LOL\tneutral\t12\tRT @enforcerswife: Quick! Someone send a cold front! #irma #heatexhaustion #heatstroke #dyingovahere\n2017-09-14 16:46:13\tBobGiesen\tnegative\t26\t@JayStylus I read #Trump\u0027s villa was unscathed by #Irma. Blaming more hurricanes on him is now going to be an even tougher sell. #MAGA\n2017-09-14 16:46:14\tMenkentLogistic\tnegative\t18\tRT @fema: The @USACEHQ is helping with generator installations, roofing, \u0026 debris removal after #Irma. More info here:… \n2017-09-14 16:46:17\tKaneM45\tneutral\t22\tRT @ABC: Key West resident becomes emotional after Army gives him supplies after #Irma: \"We should\u0027ve evacuated but we thoug… \n2017-09-14 16:46:17\tTJaslet\tneutral\t18\tRT @matg2f: quoi qu on fasse les breton i seront tjr hors d atteinte https://t.co/6Ml2S0Xn7a\n2017-09-14 16:46:17\tmgallops\tneutral\t16\tThe latest Public Safety Daily! https://t.co/tgJgLGZ5EZ Thanks to @AnimalMedicalOK @CBWCommerceMI @DigiVie #irma #natlprep\n2017-09-14 16:46:18\tssndrss\tneutral\t14\tRT @NotElizabeth88: Breaking: Heroic man saves sneakers from hurricane. #Irma https://t.co/xqas7SvWKv\n2017-09-14 16:46:18\tmapintl\tneutral\t17\tThank you @CNNImpact for your coverage and public service for those responding to #Irma and #Harvey.\n2017-09-14 16:46:19\tDifferent_Men\tneutral\t24\tRT @EmmanuelMacron: Bravo et merci à toute la communauté #ZEvent qui a permis de lever plus de 450k€ pour la @croixrouge ! #Irma\nhttps://t.…\n2017-09-14 16:46:19\tdouglascouch\tpositivie\t18\tRT @GottaLaff: Trump: \"They\u0027ve never seen anything like [#Irma] before.\"  I have only the best disasters.\n2017-09-14 16:46:20\tpralineiseroise\tneutral\t23\tRT @SpartacusVVV: #Irma  #SaintMartin l’aide humanitaire envoyée par le #Venezuela a été décidé dans le cadre de l´#ALBA… \n2017-09-14 16:46:20\tCrystal_Fishy\tneutral\t14\tRT @NickKuk: This guys saving dogs!!! #hurricane #storm #miami #irma https://t.co/FreNqNXgFG\n2017-09-14 16:46:21\tcoreamassire\tneutral\t11\tRT @boisergent: L\u0027heure du départ... https://t.co/v5NOfhWovX\n2017-09-14 16:46:22\terinrylie15\tneutral\t16\tRT @Hannasuewilson: There\u0027s a special place in heaven for this man https://t.co/AbGTdjzAHH\n2017-09-14 16:46:23\tSocialKeyWest\tneutral\t16\t#Social #KeyWest @SocialNewsCorp https://t.co/1TUfRvTAFt Via #Twitter and Facebook @Moorefun51 @urlaub365tage @BojorquezCBS #irma\n2017-09-14 16:46:24\tPaidProtester69\tpositivie\t17\tRT @quinncy: Yes, that\u0027s the horror of #Irma. Not enough dead people. https://t.co/rtAMoivjBl\n2017-09-14 16:46:24\tpatti_rouleau\tneutral\t17\tRT @CB618444: 😬This dog 🐶 has a point 🐩...\n#Harvey #Irma #Jose #Dogs #Texas #Florida https://t.co/lCKzgnSoYZ\n2017-09-14 16:46:24\tespiegler\tpositivie\t22\tSTILL? Clearly this idiotic headline was written by someone who isn\u0027t living in the hurricane zone. #Irma https://t.co/bpLyQiEEc3\n2017-09-14 16:46:25\tPedro_ACM\tneutral\t18\tRT @PrensaLatina_cu: Consejo de Iglesias de #Cuba contribuirá en la recuperación tras #Irma https://t.co/blern9aBbZ\n2017-09-14 16:46:25\tMikaRodrigus\tpositivie\t23\tRT @CNCOmusic: #CNCOwners let\u0027s help those affected by Hurricane #Irma by texting the word IRMA to 90999 to make a donation. 🙏 @RedCross\n2017-09-14 16:46:25\ttrassens\tneutral\t24\tPres. Trump is visiting Florida,but probably he don\u0027t know about the electric \u0026 Internet problems till now.What kin… https://t.co/kpR5ab9zmy\n2017-09-14 16:46:26\tThe_Ring_\tneutral\t23\tRT @AstroKomrade: Florida Keys, the way they have and will look again.  After #Irma is heartbreaking, but I look forward to returning… \n2017-09-14 16:46:26\tBABOUNE04\tneutral\t18\tRT @tvlofficiel: Excellent .@andrebercoff \"La communication de #Macron, ça s\u0027appelle lèche moi et marche !\"  #SaintMartin… \n2017-09-14 16:46:26\tellendebeckx\tneutral\t16\tRT @Hannasuewilson: There\u0027s a special place in heaven for this man https://t.co/AbGTdjzAHH\n2017-09-14 16:46:27\tFarzanaJouhi\tneutral\t14\tRT @iHartDnB: G-R-E-N-F-E-L-L https://t.co/8Xt8dg8S5b\n2017-09-14 16:46:27\tshxpeofscalia\tneutral\t23\tRT @Mowgli_Alg: Dites vous c\u0027 est un autre animal qui le sauve pendant que l\u0027humain il film mdr https://t.co/I11B4WaArj\n2017-09-14 16:46:29\theyitsallie8\tpositivie\t12\tHappy to see the voiceless animals being helped. https://t.co/8G0YEjjYrm\n2017-09-14 16:46:29\tlunaraguerrier\tneutral\t16\tRT @Hannasuewilson: There\u0027s a special place in heaven for this man https://t.co/AbGTdjzAHH\n2017-09-14 16:46:30\tXportNow\tneutral\t21\tTrucking plays a key role in Florida\u0027s recovery from Irma\nhttps://t.co/mJWha1Gpax\n#Trucking #Irma… https://t.co/Y3FdxevpWN\n2017-09-14 16:46:30\tdbnvds\tneutral\t21\tRT @HumaneSociety: The Florida Greyhound Association had no plans to evacuate 700 dogs, even if a Category 5 storm hit. 😠… \n2017-09-14 16:46:31\tZuryReyes5\tneutral\t19\tRT @ximenasofiatf: Este hombre recoge perros durante el huracán, grande!!!! #HuracanIrma #storm #miami #irma https://t.co/vec4emEUc1\n2017-09-14 16:46:31\tfiu_sipa\tneutral\t26\tRT @FIU: A message for everyone who wants to help: https://t.co/CmfgAUeVju #Irma \nPlease note that FIU is not a drop-off sit… \n2017-09-14 16:46:31\tgraham_ward24\tneutral\t14\tRT @iHartDnB: G-R-E-N-F-E-L-L https://t.co/8Xt8dg8S5b\n2017-09-14 16:46:32\tItsAfza\tneutral\t14\tRT @iHartDnB: G-R-E-N-F-E-L-L https://t.co/8Xt8dg8S5b\n2017-09-14 16:46:34\tSkazotwit\tneutral\t20\tRT @ABC: Pres. Trump and Vice Pres. Pence serve food to Florida residents impacted by Hurricane #Irma in Naples.… \n2017-09-14 16:46:35\tCCastaner\tneutral\t20\t\".@EmmanuelMacron a exprimé toute la mobilisation des forces de l\u0027état pour permettre aux îles de revivre.\" #ConseilDesMinistres #irma\n2017-09-14 16:46:36\tRobShimerVO\tneutral\t15\t@MarcScott Charged phone in car. Got mom \u0026 frozen food to a friends house. #Irma\n2017-09-14 16:46:38\tamericanguiano\tneutral\t23\tRT @TravelLeisure: 54 cats at Hemingway\u0027s house make it through #Irma without a scratch https://t.co/bgY1MAcOgt https://t.co/If2fbD54Q4\n2017-09-14 16:46:39\tandresaguilar_7\tneutral\t15\tQue grande eres mi amigo que Dios te acompañe siempre https://t.co/UBPJJv5ReL\n2017-09-14 16:46:40\tDeborah47527199\tpositivie\t20\tRT @StinsonMaas: Thanks to @VanJones68 for being a voice for the oppressed and marginalized in America https://t.co/FbyVhh6i6B\n2017-09-14 16:46:41\thifzur94\tpositivie\t21\tRT @lisa_fletch: Injured,orphaned wildlife after #Harvey / #Irma getting the help they need from the most compassionate people I kno… \n2017-09-14 16:46:41\telke_verhauwen\tneutral\t16\tRT @Hannasuewilson: There\u0027s a special place in heaven for this man https://t.co/AbGTdjzAHH\n2017-09-14 16:46:42\tLucianDeKari\tpositivie\t16\tRT @IndependentInst: Is it time to end the National Flood Insurance Program? https://t.co/NAxZPJwTwZ\n2017-09-14 16:46:42\tsenecathrilla\tpositivie\t21\tRT @dallasgoldtooth: Scientists, meteorologists AND Indig. Ppls understand the #climate connection to #Irma and #Harvey - why doesn’t the m…\n2017-09-14 16:46:43\tunnegroahi\tneutral\t23\tRT @ricardorossello: Acabamos de recibir confirmación que @realDonaldTrump visitará PR para ver el impacto de #Irma y las labores de rec… \n2017-09-14 16:46:44\tBONPOURLAFRANCE\tneutral\t23\tRT @JeanDuma1: Le Plus Grand Pont Aérien Du Monde...\n1 avion\n1 hélico\n1 mythomane\n#SaintMartin #Irma https://t.co/dAsMws1fTe\n2017-09-14 16:46:44\titsmyPresident\tneutral\t21\tRT @CCastaner: \".@EmmanuelMacron a exprimé toute la mobilisation des forces de l\u0027état pour permettre aux îles de revivre.\" #ConseilDesMinis…\n2017-09-14 16:46:44\twpbf_jimmie\tnegative\t13\tPost-hurricane diet. The Acai Bowl is back! #Irma https://t.co/5gZ6ERPiDQ\n2017-09-14 16:46:45\trosiewootten\tneutral\t14\tRT @iHartDnB: G-R-E-N-F-E-L-L https://t.co/8Xt8dg8S5b\n2017-09-14 16:46:45\tSPARTACLEX\tneutral\t24\tRT @EmmanuelMacron: Bravo et merci à toute la communauté #ZEvent qui a permis de lever plus de 450k€ pour la @croixrouge ! #Irma\nhttps://t.…\n2017-09-14 16:46:46\tRachelSavone\tneutral\t26\tRT @FLGovScott: Power has been restored to more than 4.1 million homes and businesses. We will not stop until 100% of power has bee… \n2017-09-14 16:46:48\tCVassiviere\tneutral\t28\tRT @RoseLaloba: #Irma Ne supportant pas les critiques #Macron perd son sang-froid et pète un câble face à une sinistrée https://t.co/hPGLrU…\n2017-09-14 16:46:48\tgeof24\tneutral\t16\tRT @ChristiAnne67: Sending #bibles to Hurricane https://t.co/jXAwoo9cZt victims\n#Religions poison\n🚫 Theocracy\n#ClimateChange\n📚… \n2017-09-14 16:46:49\tLaCroix\tneutral\t17\t#Irma : « À #Cuba, on n’avait jamais vu un tel ouragan depuis 1932 » https://t.co/LO1qd6T7UA\n2017-09-14 16:46:49\tJr3597\tneutral\t19\tRT @RealJoAnnBush: \"#Food \u0026 #Water Distribution Points in #LeeCounty, #FL after #Irma: https://t.co/LehNWycyzL \n#IrmaSOS #FortMyers #Florid…\n2017-09-14 16:46:51\tbrandon_demeter\tpositivie\t22\tRT @USMC: Yesterday, Marines with the 26th MEU delivered over 52,000 pounds of relief supplies to victims of Hurricane #Irma,… \n2017-09-14 16:46:52\ttomCLanderson\tnegative\t9\tour PM is a disgrace https://t.co/z5X4840pYl\n2017-09-14 16:46:52\tantunestony1033\tneutral\t21\tRT @CCastaner: \".@EmmanuelMacron a exprimé toute la mobilisation des forces de l\u0027état pour permettre aux îles de revivre.\" #ConseilDesMinis…\n2017-09-14 16:46:52\tihhhme\tneutral\t16\tRT @jodi_mohrmann: #WATCH: #Drone video by Alexander Locke of #Irma damage in #DaytonaBeach. #IrmaHurricane2017 #HurricaneIrma… \n2017-09-14 16:46:53\tSWhite_HT\tneutral\t23\tRT @SalvationArmyUS: As #Irma evacuees return home, many are without power. Our canteens are providing warm meals to all who are hungry.… \n2017-09-14 16:46:53\tloudmouthdad\tneutral\t15\tRT @LoveUSADawn: #POTUSTrump #FLOTUS #VP PENCE \u0026 SECOND LADY PENCE\n#FLORIDA #IRMA #HURRICANE\n#IrmaRecovery #PrayForFlorida 🇺🇸🙏🏼… \n2017-09-14 16:46:53\tDianthus67\tneutral\t17\tRT @EtatMajorFR: Avant, pendant et après #Irma : les armées présentes. https://t.co/c1rVAoLTgK\n2017-09-14 16:46:53\tMIB_97\tneutral\t16\tRT @Hannasuewilson: There\u0027s a special place in heaven for this man https://t.co/AbGTdjzAHH\n2017-09-14 16:46:55\tpwm4u\tneutral\t23\tRT @ENERGY: Thursday AM #Irma Update:\n◾ Power restored to 75% of FL\n◾ 200K+ outages in GA\n◾ USVI mostly w/o power\nREPORT ➡… \n2017-09-14 16:46:56\texpIisite\tneutral\t14\tRT @NickKuk: This guys saving dogs!!! #hurricane #storm #miami #irma https://t.co/FreNqNXgFG\n2017-09-14 16:46:56\tdhammitt27\tneutral\t16\tRT @Hannasuewilson: There\u0027s a special place in heaven for this man https://t.co/AbGTdjzAHH\n2017-09-14 16:46:57\tvisser4fam\tnegative\t19\tWhen will @seminolecounty pass this on to its paying customers? How is this money spent? https://t.co/S23Pd44Jdm\n2017-09-14 16:46:57\thalconesdnorte\tneutral\t18\tRT @PrensaLatina_cu: Consejo de Iglesias de #Cuba contribuirá en la recuperación tras #Irma https://t.co/blern9aBbZ\n2017-09-14 16:46:58\tloindevant\tneutral\t24\t#Irma #SaintMartin #decodex du Monde https://t.co/dm7U5MEXLd ces centaines de témoins sur youtube mentent donc… à qui profite le mensonge?\n2017-09-14 16:46:59\tLyliane_M\tneutral\t20\tRT @UniNoticias: Presidente Trump visitará Puerto Rico para ver las labores de recuperación por el huracán #Irma.… \n2017-09-14 16:46:59\tK30thy\tneutral\t16\tRT @Hannasuewilson: There\u0027s a special place in heaven for this man https://t.co/AbGTdjzAHH\n2017-09-14 16:46:59\tphilshouse57\tneutral\t22\tRT @ABC: Kissimmee, Florida police officer dances with an elderly woman at a local emergency shelter to help ease her anxiet… \n2017-09-14 16:47:00\tTNNTelecomNews\tneutral\t20\tRT @NJFiberExchange: #NJFX’s Colocation Campus Supports Global Connectivity against #Hurricane #Irma \nhttps://t.co/Pnvq8xRLYP https://t.co…\n2017-09-14 16:47:00\tMiami_FocusG\tneutral\t8\tFree meals #Irma #Jetblue https://t.co/FDSwctTCTN\n2017-09-14 16:47:01\tThomasRFletcher\tpositivie\t22\t\"Remnants\" #Irma #WVphotographer #WestVirginia Last light on the remnants of Irma over West Virginia, sundown 9/13/… https://t.co/lXT2Y9GxAx\n2017-09-14 16:47:01\thifzur94\tneutral\t4\thttps://t.co/jx1k1eBBSH\n2017-09-14 16:47:02\tclmntleclerc\tneutral\t25\tRT @FranceinMiami: #Irma L\u0027aéroport de #Miami @IflyMIA annonce que toutes les companies aériennes reprendront la totalité de leurs vols rég…\n2017-09-14 16:47:02\tGaudinAxel\tneutral\t24\tRT @EmmanuelMacron: Bravo et merci à toute la communauté #ZEvent qui a permis de lever plus de 450k€ pour la @croixrouge ! #Irma\nhttps://t.…\n2017-09-14 16:47:03\tGoAvisBudget\tneutral\t8\tRT @abgFlorida: @GoAvisBudget @LisaHRSEA https://t.co/8PsFmhdCWj\n2017-09-14 16:47:03\tTNNTelecomNews\tneutral\t20\tRT @NJFiberExchange: We are working with major carriers, expediting installs to support a major telecom hub in FL #Irma… \n2017-09-14 16:47:03\taflakaa\tneutral\t14\tRT @iHartDnB: G-R-E-N-F-E-L-L https://t.co/8Xt8dg8S5b\n2017-09-14 16:47:03\tjvaloss\tneutral\t16\tRT @Hannasuewilson: There\u0027s a special place in heaven for this man https://t.co/AbGTdjzAHH\n2017-09-14 16:47:05\tandrearb7\tneutral\t20\tRT @GarofaloWX: THANK YOU!! Give big thanks to 1st responders, local emergency management saving lives during #Irma #flwx @scgovEOC… \n2017-09-14 16:47:05\tkrissysmissives\tpositivie\t19\t\"Knock the crap out of \u0027em, will ya?\" Yeah, a real people person XD https://t.co/MmUtr8IEoF\n2017-09-14 16:47:05\tGeriFuller8\tneutral\t23\tRT @vicktoriyah_: Don\u0027t forget about Lehigh Acres when it come to relief. @winknews @NBC2 #IrmaRecovery #Irma We are being overlooked. @ABC…\n2017-09-14 16:47:05\t669atWCC\tpositivie\t23\tRT @UAPipeTrades: #Harvey #Irma devastated the homes of many of our members. Here\u0027s 1 from Houston. Please donate \u0026 help them rebuild… \n2017-09-14 16:47:05\tFlamengo17\tneutral\t20\tRT @beatlemaria: Pdte @realDonaldTrump pone en 1er lugar a su pueblo. Aprendan @TareckPSUV y @NicolasMaduro ayuden a gente en… \n2017-09-14 16:47:06\tRyan_NelsonSC\tneutral\t14\tRT @LCWxDave: Beach erosion hit IOP pretty hard. #Irma #chswx https://t.co/RuSkYSGXz8\n2017-09-14 16:47:06\tValdostaMeeting\tneutral\t13\tWishing a speedy recovery for all those involved. #Irma https://t.co/ypDzS6MvcA\n2017-09-14 16:47:06\tvlmhma\tnegative\t24\tHow stupid are Floridians? We\u0027ll find out when #MORONRICKScott runs again for Gov. If he wins/ forget helping these… https://t.co/a1YBhTkNDm\n2017-09-14 16:47:07\tKINGPRIMO\tpositivie\t21\tRT @RedCross: ~6,000 Red Cross workers \u0026 276 emergency response vehicles are on the ground, helping thousands of people affected… \n2017-09-14 16:47:07\tCityNMB\tneutral\t19\tRT @FLSERT: Hurricane #Irma Power Outage Report as of 9/14/2017 11:54 AM https://t.co/GWRwgYmYEb\n2017-09-14 16:47:07\tXRIM\tneutral\t22\t#MONEY #IRMA CNNPolitics\nWhat is the DREAM Act? https://t.co/5L3Y5QBkH7 https://t.co/Q4JORHvPyv\n— CNN Politics (CNNPolitics) September …\n2017-09-14 16:47:08\tExpert_Investor\tneutral\t21\trecord #Irma loss for #catbonds could be blessing disguise for asset class @bajanzurich https://t.co/kjOaQS93CI https://t.co/k9YFqz7yix\n2017-09-14 16:47:08\tleeannelambert\tneutral\t14\tRT @LCWxDave: Beach erosion hit IOP pretty hard. #Irma #chswx https://t.co/RuSkYSGXz8\n2017-09-14 16:47:08\tblivette_ag\tneutral\t17\tRT @Jan_Herzog: Fueron observados #Flamingos Evacuando en #Tampa, #Florida por el #Huracan #Irma ... https://t.co/XM7sgO2CnY\n2017-09-14 16:47:08\tJavecCastaner\tneutral\t21\tRT @CCastaner: \".@EmmanuelMacron a exprimé toute la mobilisation des forces de l\u0027état pour permettre aux îles de revivre.\" #ConseilDesMinis…\n2017-09-14 16:47:08\tannickgeronimi\tneutral\t22\tRT @franceinfo: #Irma \"Nous avons ouvert très vite Family Links pour retrouver les personnes disparues\" Florent Vallée, Croix Rouge… \n2017-09-14 16:47:08\tRobertJHemsley\tneutral\t20\tWe are ready to go here in Ft Myers after Hurricane #Irma ! @SheMorgan1 @JohnLegere #WeWontStop #Tmobile https://t.co/GlC0TUZoe6\n2017-09-14 16:47:09\tPolMansol2012\tneutral\t22\tRT @USEmbassyBogota: -@POTUS y @FLOTUS partieron hacia La Florida para reunirse con los afectados del huracán #Irma. https://t.co/elQ8F8ZcWF\n2017-09-14 16:47:09\tGaiLuronNicky\tneutral\t21\tRT @DIvory_WGN: These guys got arrested for trying to steal and ENTIRE TELEPHONE POLE after Hurricane #Irma. https://t.co/AkeU9TkO9J\n2017-09-14 16:47:10\tPhntm888\tneutral\t21\tRT @FDAfood: #FoodSafety questions after #hurricane #Harvey \u0026 #Irma? Call our food safety experts for help 888-SAFE-FOOD. We\u0027re… \n2017-09-14 16:47:10\tvaevictis94\tneutral\t15\tCeux qui ont voté #Macron sont vraiment des cons #BFMTV #LCI https://t.co/EohRroJImM\n2017-09-14 16:47:12\tDouniaCarels\tneutral\t16\tRT @m_vd_eerden: #teampeli concentreert op maritieme zaken: drinkwaterleiding haven, leegpompen bassins, herstel generators en berge… \n2017-09-14 16:47:13\tMiamiGives\tneutral\t16\tRT @SFLRedCross: Hurricane #Irma – One Volunteer’s Perspective: https://t.co/fYa22Cr35d https://t.co/NEc1unMtJc\n2017-09-14 16:47:14\tcmm_online\tneutral\t20\tRT @HealthyFla: #FLHealth urges residents to not drink contaminated water after #Irma: https://t.co/LddXA6ifKL https://t.co/jTLScHZ01s\n2017-09-14 16:47:14\tEMS_Information\tnegative\t21\tfema:The USACEHQ is helping with generator installations, roofing, \u0026 debris removal after #Irma. More info here:… … https://t.co/ZqPrVkTc8x)\n2017-09-14 16:47:14\tBacondawg\tnegative\t18\tRT @fema: The @USACEHQ is helping with generator installations, roofing, \u0026 debris removal after #Irma. More info here:… \n2017-09-14 16:47:16\tmmirandaa4\tneutral\t16\tRT @Hannasuewilson: There\u0027s a special place in heaven for this man https://t.co/AbGTdjzAHH\n2017-09-14 16:47:16\tJesus59782016\tneutral\t22\tRT @ABC: Key West resident becomes emotional after Army gives him supplies after #Irma: \"We should\u0027ve evacuated but we thoug… \n2017-09-14 16:47:16\tCityNMB\tpositivie\t19\tRT @FLSERT: Text \"FLResponds\" to 888777 to receive Hurricane Irma updates from the State Emergency Response Team #Irma #FLResponds\n2017-09-14 16:47:16\trantg1\tneutral\t23\tRT @ENERGY: Thursday AM #Irma Update:\n◾ Power restored to 75% of FL\n◾ 200K+ outages in GA\n◾ USVI mostly w/o power\nREPORT ➡… \n2017-09-14 16:47:16\tSecure_LA\tneutral\t23\tRT @ENERGY: Thursday AM #Irma Update:\n◾ Power restored to 75% of FL\n◾ 200K+ outages in GA\n◾ USVI mostly w/o power\nREPORT ➡… \n2017-09-14 16:47:18\tcuchy68\tneutral\t24\tRT @ricardorossello: En conferencia de prensa sobre la agenda del #FrentePorPR y los esfuerzos en la Isla para la repatriación de nuestr… \n2017-09-14 16:47:18\ttemperance71470\tneutral\t21\tRT @dannywood: Got my first post #irma workout in @soultrainboxing with Coach Brown! 20 rounds of boxing 🥊… https://t.co/Is472wvEKf\n2017-09-14 16:47:19\tkrisprincesse\tneutral\t22\tRT @franceinfo: #Irma \"Nous avons ouvert très vite Family Links pour retrouver les personnes disparues\" Florent Vallée, Croix Rouge… \n"
          }
        ]
      },
      "apps": [],
      "jobName": "paragraph_1505352151355_-573415257",
      "id": "20170914-012231_1463084058",
      "dateCreated": "Sep 14, 2017 1:22:31 AM",
      "dateStarted": "Sep 14, 2017 4:47:26 PM",
      "dateFinished": "Sep 14, 2017 4:47:26 PM",
      "status": "FINISHED",
      "progressUpdateIntervalMs": 500
    },
    {
      "text": "%sql\n\n--ploting sentiment\n\nselect  sentiment(text) as sentiment, count(1) from tweets group by sentiment(text)\n",
      "user": "anonymous",
      "dateUpdated": "Sep 14, 2017 4:49:58 PM",
      "config": {
        "colWidth": 12.0,
        "enabled": true,
        "results": {
          "0": {
            "graph": {
              "mode": "pieChart",
              "height": 300.0,
              "optionOpen": false
            },
            "helium": {}
          }
        },
        "editorSetting": {
          "language": "text",
          "editOnDblClick": false
        },
        "editorMode": "ace/mode/text"
      },
      "settings": {
        "params": {},
        "forms": {}
      },
      "results": {
        "code": "SUCCESS",
        "msg": [
          {
            "type": "TABLE",
            "data": "sentiment\tcount(1)\nneutral\t160\nnegative\t7\npositivie\t35\n"
          }
        ]
      },
      "apps": [],
      "jobName": "paragraph_1505352167304_-720927328",
      "id": "20170914-012247_122513089",
      "dateCreated": "Sep 14, 2017 1:22:47 AM",
      "dateStarted": "Sep 14, 2017 4:49:58 PM",
      "dateFinished": "Sep 14, 2017 4:49:59 PM",
      "status": "FINISHED",
      "progressUpdateIntervalMs": 500
    },
    {
      "text": "%sql\n\n--show most common words for positive and negatives tweets\n\nselect word, sentiment, count(1) as cnt\nfrom \n(\n   select from_unixtime(createdAt) as created, screenName, sentiment(text) as sentiment, wordcount(text) as wordcount, text  from tweets\n) sub1\nlateral view explode(split(text, \u0027 \u0027)) t as word \nwhere sentiment \u003c\u003e \u0027neutral\u0027\ngroup by word, sentiment\n--having count(1) \u003e 1\norder by cnt desc\n\n\n",
      "user": "anonymous",
      "dateUpdated": "Sep 14, 2017 4:50:11 PM",
      "config": {
        "colWidth": 12.0,
        "enabled": true,
        "results": {
          "0": {
            "graph": {
              "mode": "multiBarChart",
              "height": 300.0,
              "optionOpen": false,
              "setting": {
                "multiBarChart": {}
              },
              "commonSetting": {},
              "keys": [
                {
                  "name": "word",
                  "index": 0.0,
                  "aggr": "sum"
                }
              ],
              "groups": [],
              "values": [
                {
                  "name": "cnt",
                  "index": 2.0,
                  "aggr": "sum"
                }
              ]
            },
            "helium": {}
          }
        },
        "editorSetting": {
          "language": "text",
          "editOnDblClick": false
        },
        "editorMode": "ace/mode/text"
      },
      "settings": {
        "params": {},
        "forms": {}
      },
      "results": {
        "code": "SUCCESS",
        "msg": [
          {
            "type": "TABLE",
            "data": "word\tsentiment\tcnt\nthe\tpositivie\t41\nRT\tpositivie\t30\nto\tpositivie\t26\n#Irma\tpositivie\t18\n\tpositivie\t14\na\tpositivie\t14\nof\tpositivie\t12\nHurricane\tpositivie\t11\nin\tpositivie\t10\nby\tpositivie\t8\nand\tpositivie\t7\nis\tnegative\t6\non\tpositivie\t6\nlike\tpositivie\t5\nis\tpositivie\t5\nafter\tpositivie\t4\nthose\tpositivie\t4\nSpider-Man,\tpositivie\t4\nfrom\tpositivie\t4\nRT\tnegative\t4\n\u0026\tnegative\t4\naffected\tpositivie\t4\nwhat\tpositivie\t4\nIRMA\tpositivie\t3\ntexting\tpositivie\t3\ndonation.\tpositivie\t3\nhelp\tpositivie\t3\nwith\tpositivie\t3\n90999\tpositivie\t3\n@CNCOmusic:\tpositivie\t3\nIrma\tpositivie\t3\nwith\tnegative\t3\nyou\tpositivie\t3\n🙏\tpositivie\t3\nthat\tpositivie\t3\n.\tpositivie\t3\nare\tpositivie\t3\nlet\u0027s\tpositivie\t3\n@RedCross\tpositivie\t3\n\tnegative\t3\nword\tpositivie\t3\nmake\tpositivie\t3\n#Irma.\tpositivie\t3\nIt\tpositivie\t3\n#CNCOwners\tpositivie\t3\nbe\tpositivie\t3\n-\tpositivie\t2\nthat\u0027s\tpositivie\t2\nspider-man\tpositivie\t2\npeople.\tpositivie\t2\nYou\tpositivie\t2\nhttps://t.co/n1qqHSkbSG\tpositivie\t2\n\"FLResponds\"\tpositivie\t2\nYes,\tpositivie\t2\n#NHS\tpositivie\t2\n#OLSX\tpositivie\t2\nroofing,\tnegative\t2\nhttps://t.co/rtAMoivjBl\tpositivie\t2\ncan\tpositivie\t2\n@USACEHQ\tnegative\t2\nhurricane\tpositivie\t2\nIsland\tpositivie\t2\nupdates\tpositivie\t2\n#Irma.\tnegative\t2\nI\tpositivie\t2\nenough\tpositivie\t2\nWallace\tpositivie\t2\nwhatever\tpositivie\t2\nEmergency\tpositivie\t2\nvia\tpositivie\t2\nhave\tpositivie\t2\nstill\tpositivie\t2\n#Harvey\tpositivie\t2\ndoes\tpositivie\t2\naround\tpositivie\t2\nTeresa\tpositivie\t2\nand\tnegative\t2\ndown\tpositivie\t2\nspider\tpositivie\t2\n#VirginCare\tpositivie\t2\nResponse\tpositivie\t2\n\u0026\tpositivie\t2\nState\tpositivie\t2\nhas\tpositivie\t2\n#Irma\tnegative\t2\nafter\tnegative\t2\nNecker\tpositivie\t2\ndid\tpositivie\t2\nThe\tnegative\t2\nhorror\tpositivie\t2\ndead\tpositivie\t2\n@OccupyLondon:\tpositivie\t2\nremoval\tnegative\t2\nTeam\tpositivie\t2\nfor\tpositivie\t2\ndog\tpositivie\t2\n888777\tpositivie\t2\ndebris\tnegative\t2\nwas\tpositivie\t2\nfriendly\tpositivie\t2\nneighborhood\tpositivie\t2\ncaught\tpositivie\t2\n#FLResponds\tpositivie\t2\nmy\tpositivie\t2\ninfo\tnegative\t2\ncan!\tpositivie\t2\nour\tpositivie\t2\n@BN9:\tpositivie\t2\nCaribbean\tpositivie\t2\nhere:…\tnegative\t2\ndoing\tpositivie\t2\nfor\tnegative\t2\n@FLSERT:\tpositivie\t2\ngenerator\tnegative\t2\nText\tpositivie\t2\n@fema:\tnegative\t2\ninstallations,\tnegative\t2\nhelp…\tpositivie\t2\nlooks\tpositivie\t2\ngood\tpositivie\t2\nlife\tpositivie\t2\nNot\tpositivie\t2\nTrump\tpositivie\t2\nstorm\tpositivie\t2\nhelping\tnegative\t2\nfirst\tpositivie\t2\nat\tpositivie\t2\nreceive\tpositivie\t2\n@quinncy:\tpositivie\t2\nhis\tpositivie\t2\nwhile\tpositivie\t2\nmessed\tpositivie\t2\nMore\tnegative\t2\nno\tpositivie\t2\n…\tpositivie\t1\nfull\tpositivie\t1\nits\tpositivie\t1\nIndig.\tpositivie\t1\nseveral\tpositivie\t1\nhttps://t.co/Ygyo61kKkR\tpositivie\t1\nNaples,\tpositivie\t1\nSee\tpositivie\t1\n@CTVOttMornLive:\tpositivie\t1\ncommunity\tpositivie\t1\ndisaster\tpositivie\t1\ntoday\tpositivie\t1\nturns\tpositivie\t1\nactivities\tnegative\t1\nAmerican\tpositivie\t1\nhotel\tnegative\t1\nVP\tpositivie\t1\n#Islamorada\tpositivie\t1\ndestruction\tpositivie\t1\nresponse\tpositivie\t1\nanniversary\tpositivie\t1\n9/11\tpositivie\t1\npeople\tpositivie\t1\n@HomeDepot\tpositivie\t1\nhotel\tpositivie\t1\nWe\tnegative\t1\nmust\tpositivie\t1\nChapel\tpositivie\t1\nWe\tpositivie\t1\nhttps://t.co/j2M3u7d9…\tpositivie\t1\n#life\n#Irma\nhttps://t.co/elCyutzT0R\tnegative\t1\nperson\tpositivie\t1\ntransparency\tpositivie\t1\nworkers\tpositivie\t1\nthis\tpositivie\t1\nlooked\tpositivie\t1\nseason\tnegative\t1\nretail\tnegative\t1\n@ChelseaClinton:\tnegative\t1\nfrom\tnegative\t1\nPpls\tpositivie\t1\nconnection\tpositivie\t1\ntweet\tpositivie\t1\nsince\tnegative\t1\nFort\tnegative\t1\ncurtain\tpositivie\t1\nCaribbean.\tpositivie\t1\nsucks\tpositivie\t1\nConcealing\tnegative\t1\nassist\tpositivie\t1\n300\tpositivie\t1\ncleanup\tpositivie\t1\nGeorgia\tpositivie\t1\nam\tpositivie\t1\nhave.😉😉😉\tpositivie\t1\ngovernment\tpositivie\t1\nnormal\tpositivie\t1\nkrab\tpositivie\t1\nvideos\tpositivie\t1\nIn\tpositivie\t1\nThank\tpositivie\t1\nPublic\tpositivie\t1\nrestoring\tpositivie\t1\nhttps://t.c…\tpositivie\t1\nhttps://t.co/5QU3Ybz935\tpositivie\t1\nbrown:…\tpositivie\t1\nhttps://t.co/RiqSzO26br\tpositivie\t1\never\tpositivie\t1\nexposure.\n#EU\tnegative\t1\nrefurbished.\tnegative\t1\nNissan\tpositivie\t1\nsurge\tpositivie\t1\nwho\tpositivie\t1\nphotos\tpositivie\t1\n#relief…\tpositivie\t1\nhead\tpositivie\t1\ndon\u0027t\tpositivie\t1\nwake,\tpositivie\t1\nquestion\tpositivie\t1\ngreat\tpositivie\t1\nconcern\tpositivie\t1\nThis\tnegative\t1\n#Irma\u0027s\tpositivie\t1\n@WTSP10News\tpositivie\t1\nvolunteering/supplying\tpositivie\t1\nphysically\tpositivie\t1\nisland\tpositivie\t1\nasshole\tpositivie\t1\nwere\tnegative\t1\nhe\u0027s\tpositivie\t1\n2nd\tpositivie\t1\n#ottnews\tpositivie\t1\njob\tpositivie\t1\nhttps://t…\tnegative\t1\ndemocracy\tpositivie\t1\n~6,000\tpositivie\t1\nterrible\tnegative\t1\nflag\tpositivie\t1\nAtlantic\tpositivie\t1\nScientists,\tpositivie\t1\nday.\tpositivie\t1\nSignal\tpositivie\t1\naerial\tnegative\t1\nHydro\tpositivie\t1\ncrews\tpositivie\t1\nstuck\tpositivie\t1\nnearly\tpositivie\t1\nislands\tpositivie\t1\n@IOPCity\tpositivie\t1\npizza\tpositivie\t1\n@SecretaryPerry:\tpositivie\t1\n7\tpositivie\t1\nvictims\tpositivie\t1\n@SkyNews:\tpositivie\t1\ndo.\tpositivie\t1\nHillary\tpositivie\t1\nhttps://t.co/5Sv03NlEaj\tpositivie\t1\n@wemoveEU:\tpositivie\t1\nyou!!\tpositivie\t1\nhttps://t.co/oyrRA2ccth\tnegative\t1\n#Barbuda\u0027\tpositivie\t1\nit\tnegative\t1\n@TimInHonolulu:\tpositivie\t1\n#climatechange?\tpositivie\t1\nOttawa\tpositivie\t1\n@realDonaldTrump\tpositivie\t1\nthere\tnegative\t1\ndamage.\tpositivie\t1\ndamage…\tnegative\t1\nunderstand\tpositivie\t1\nEngineers\tpositivie\t1\nscours\tpositivie\t1\n@RedCross:\tpositivie\t1\nrelief.\tpositivie\t1\nstruggles\tpositivie\t1\nnot\tpositivie\t1\nrelief\tpositivie\t1\nvideo\tpositivie\t1\ntree\tpositivie\t1\nhttps://t.co/YkIrc3BOoD\tpositivie\t1\n@MarkWilsonTV:\tnegative\t1\ncounty.\tpositivie\t1\npocket\tpositivie\t1\nnow\tpositivie\t1\ngot\tpositivie\t1\ntrucks\tpositivie\t1\nfro…\tnegative\t1\n@MikeTheiss:\tpositivie\t1\n#EU\tpositivie\t1\nIf\tpositivie\t1\nCross\tpositivie\t1\nStay…\tpositivie\t1\njust\tnegative\t1\nthousands\tpositivie\t1\nWhat\tpositivie\t1\nshelters.\tpositivie\t1\nliving\tpositivie\t1\ndone\tpositivie\t1\n@covfefeartist:\tpositivie\t1\nhttps://t.co/eyiQh3V9wh\tpositivie\t1\n@BN9\tpositivie\t1\nonboard\tnegative\t1\n#AskJuncker\tpositivie\t1\nMyers\tnegative\t1\nexpected\tpositivie\t1\nAnneliese-\tpositivie\t1\nm…\tpositivie\t1\nestablish\tpositivie\t1\nstand\tpositivie\t1\nemergency\tpositivie\t1\nextent\tpositivie\t1\nvehicles\tpositivie\t1\nin\tnegative\t1\nIrma.\tpositivie\t1\npost\tnegative\t1\n@FLGovScott.\tpositivie\t1\nmade\tpositivie\t1\nFox13\tnegative\t1\ngoes\tpositivie\t1\nof\tnegative\t1\nfriend\tpositivie\t1\ntips\tpositivie\t1\nShould\tpositivie\t1\nhttps://t.co/fvYfiUFQ8F\tpositivie\t1\ntough,\tnegative\t1\nGood\tpositivie\t1\nimmediately.\tpositivie\t1\nor\tpositivie\t1\nless.\tpositivie\t1\nairport\tnegative\t1\ncountry.\tpositivie\t1\ncan\u0027t,\tpositivie\t1\nfar\tnegative\t1\nInlet\tpositivie\t1\n#Ir…\tpositivie\t1\ntryna\tpositivie\t1\ntaking\tpositivie\t1\ntour\tnegative\t1\npower\tpositivie\t1\nhttps://t.co/sDkcB8EHed\tpositivie\t1\n\"Watch\tpositivie\t1\nhttps://t.co/UsceintTuh\tnegative\t1\nresponding\tpositivie\t1\nrequires\tnegative\t1\naction\tpositivie\t1\n#irma\tpositivie\t1\nhelping\tpositivie\t1\n#Harvey\tnegative\t1\n@NASA:\tpositivie\t1\n@Paula_White:\tpositivie\t1\n@ENERGY\tpositivie\t1\nMarines\tpositivie\t1\nlove\tpositivie\t1\nparticularly\tnegative\t1\napproaches\tnegative\t1\nain\u0027t\tpositivie\t1\nseen\tpositivie\t1\nGreat\tpositivie\t1\nso\tpositivie\t1\nillusionist\tpositivie\t1\ncaption.\tpositivie\t1\nrunning\tnegative\t1\nRed\tpositivie\t1\ntore\tpositivie\t1\nrecord\tpositivie\t1\nTake\tpositivie\t1\nthere’s\tpositivie\t1\nhttps://t.co/eCfdpRs…\tpositivie\t1\nV-22\tnegative\t1\nobstacles\tpositivie\t1\nan\tpositivie\t1\n2\tnegative\t1\ncollapsed\tpositivie\t1\nt…\tpositivie\t1\nefforts\tpositivie\t1\naffected…\tpositivie\t1\nplease\tpositivie\t1\nkrusty\tpositivie\t1\nstrongest\tpositivie\t1\nano…\tpositivie\t1\nSpent\tpositivie\t1\nman\u0027s\tpositivie\t1\nor\tnegative\t1\nnow.\tpositivie\t1\nstanding\tpositivie\t1\nMy\tpositivie\t1\n@IRSnews:\tpositivie\t1\n@VP\tnegative\t1\nnightmare\tpositivie\t1\nbrought\tpositivie\t1\nPSA:\tpositivie\t1\n#WesternExpress\tpositivie\t1\nevacuate\tpositivie\t1\nfocus\tpositivie\t1\nclean-up\tpositivie\t1\nteam\tpositivie\t1\nyears,\tpositivie\t1\nP\tpositivie\t1\nVolunteers\tpositivie\t1\n@CodexiaStudios:\tpositivie\t1\nPlease\tpositivie\t1\ndeliver\tpositivie\t1\nwould\tpositivie\t1\nmakes\tpositivie\t1\nlandfall\tpositivie\t1\nWesley\tpositivie\t1\n@Juice2Wavy:\tpositivie\t1\nFloridians,\tpositivie\t1\nland\tpositivie\t1\nall\tpositivie\t1\ndangerous\tnegative\t1\n@aoojadi:\tpositivie\t1\nNashville,\tnegative\t1\nloading\tpositivie\t1\ndoesn’t\tpositivie\t1\ntent\tpositivie\t1\nground,\tpositivie\t1\nrenovated\tnegative\t1\n#IRS\tpositivie\t1\npublic\tpositivie\t1\npunished\tpositivie\t1\nbut\tpositivie\t1\nsittin\tpositivie\t1\nout\tpositivie\t1\nsingle\tpositivie\t1\nBreach\tpositivie\t1\nI\u0027m\tpositivie\t1\non\tnegative\t1\nraise\tpositivie\t1\nMarine\tnegative\t1\nshooting\tpositivie\t1\nhelo\tnegative\t1\nmeteorologists\tpositivie\t1\n#climate\tpositivie\t1\ndeed\tpositivie\t1\n@JanWindglows:\tpositivie\t1\nup.\tpositivie\t1\nboth\tpositivie\t1\nFL.\tpositivie\t1\n#Irma…\tpositivie\t1\ndonations\tpositivie\t1\nsoon\tpositivie\t1\nhealth\tnegative\t1\nsave\tpositivie\t1\n276\tpositivie\t1\nas\tnegative\t1\n#bananas\tpositivie\t1\n@ExtendedStay\tnegative\t1\nrec…\tpositivie\t1\nYour\tnegative\t1\n@Ryan_NelsonSC:\tpositivie\t1\ntime\tpositivie\t1\npublic\tnegative\t1\nOsprey\tnegative\t1\n😅\tpositivie\t1\nObama\tpositivie\t1\nlooking\tpositivie\t1\n\u0027For\tpositivie\t1\ngo\tpositivie\t1\ns…\tpositivie\t1\nThe\tpositivie\t1\narea\tpositivie\t1\nessentials!!\tpositivie\t1\n@RoyalNavy:\tpositivie\t1\nneed\tpositivie\t1\narrive\tpositivie\t1\n@dallasgoldtooth:\tpositivie\t1\nup\tpositivie\t1\nArmy\tpositivie\t1\nthroughout\tpositivie\t1\nwhy\tpositivie\t1\n@MonaWhack:\tpositivie\t1\nhealth\tpositivie\t1\nbanana\tpositivie\t1\nHis\tpositivie\t1\nright\tpositivie\t1\nExtreme\tpositivie\t1\nhelps\tpositivie\t1\n#hurricane\tpositivie\t1\nWalked\tpositivie\t1\nNaples\tnegative\t1\nspace\tpositivie\t1\nIt\u0027s\tpositivie\t1\nRoyal\tpositivie\t1\nAND\tpositivie\t1\nbeach\tpositivie\t1\n@SecretService\tpositivie\t1\nreal\tpositivie\t1\nhere\tpositivie\t1\nleave\tpositivie\t1\nelse\tpositivie\t1\nflu\tnegative\t1\n"
          }
        ]
      },
      "apps": [],
      "jobName": "paragraph_1505352180129_1358671126",
      "id": "20170914-012300_912056455",
      "dateCreated": "Sep 14, 2017 1:23:00 AM",
      "dateStarted": "Sep 14, 2017 4:50:11 PM",
      "dateFinished": "Sep 14, 2017 4:50:12 PM",
      "status": "FINISHED",
      "progressUpdateIntervalMs": 500
    },
    {
      "text": "%sql\n\nselect minute, sentiment, count(1) as cnt from\n(\n   select substr(from_unixtime(createdAt), 0, 16) as minute, screenName, sentiment(text) as sentiment, wordcount(text) as wordcount, text  from tweets\n) sub1\ngroup by minute, sentiment\norder by minute\n",
      "user": "anonymous",
      "dateUpdated": "Sep 14, 2017 4:51:06 PM",
      "config": {
        "colWidth": 12.0,
        "enabled": true,
        "results": {},
        "editorSetting": {
          "language": "text",
          "editOnDblClick": false
        },
        "editorMode": "ace/mode/text"
      },
      "settings": {
        "params": {},
        "forms": {}
      },
      "results": {
        "code": "ERROR",
        "msg": [
          {
            "type": "TEXT",
            "data": "org.codehaus.janino.JaninoRuntimeException: Class \u0027org.apache.spark.sql.catalyst.expressions.codegen.GeneratedClass\u0027 was loaded through a different loader\n\tat org.codehaus.janino.SimpleCompiler$1.getDelegate(SimpleCompiler.java:356)\n\tat org.codehaus.janino.SimpleCompiler$1.accept(SimpleCompiler.java:301)\n\tat org.codehaus.janino.UnitCompiler.getType(UnitCompiler.java:5660)\n\tat org.codehaus.janino.UnitCompiler.access$1200(UnitCompiler.java:206)\n\tat org.codehaus.janino.UnitCompiler$30.getSuperclass2(UnitCompiler.java:8933)\n\tat org.codehaus.janino.IClass.getSuperclass(IClass.java:404)\n\tat org.codehaus.janino.IClass.findMemberType(IClass.java:765)\n\tat org.codehaus.janino.IClass.findMemberType(IClass.java:732)\n\tat org.codehaus.janino.UnitCompiler.findMemberType(UnitCompiler.java:10948)\n\tat org.codehaus.janino.UnitCompiler.getReferenceType(UnitCompiler.java:5876)\n\tat org.codehaus.janino.UnitCompiler.getReferenceType(UnitCompiler.java:5751)\n\tat org.codehaus.janino.UnitCompiler.getType2(UnitCompiler.java:5732)\n\tat org.codehaus.janino.UnitCompiler.access$13200(UnitCompiler.java:206)\n\tat org.codehaus.janino.UnitCompiler$18.visitReferenceType(UnitCompiler.java:5668)\n\tat org.codehaus.janino.UnitCompiler$18.visitReferenceType(UnitCompiler.java:5660)\n\tat org.codehaus.janino.Java$ReferenceType.accept(Java.java:3356)\n\tat org.codehaus.janino.UnitCompiler.getType(UnitCompiler.java:5660)\n\tat org.codehaus.janino.UnitCompiler.getType2(UnitCompiler.java:6007)\n\tat org.codehaus.janino.UnitCompiler.access$13000(UnitCompiler.java:206)\n\tat org.codehaus.janino.UnitCompiler$18.visitArrayType(UnitCompiler.java:5666)\n\tat org.codehaus.janino.UnitCompiler$18.visitArrayType(UnitCompiler.java:5660)\n\tat org.codehaus.janino.Java$ArrayType.accept(Java.java:3425)\n\tat org.codehaus.janino.UnitCompiler.getType(UnitCompiler.java:5660)\n\tat org.codehaus.janino.UnitCompiler.access$1200(UnitCompiler.java:206)\n\tat org.codehaus.janino.UnitCompiler$32.getParameterTypes2(UnitCompiler.java:9326)\n\tat org.codehaus.janino.IClass$IInvocable.getParameterTypes(IClass.java:853)\n\tat org.codehaus.janino.IClass$IMethod.getDescriptor2(IClass.java:1084)\n\tat org.codehaus.janino.IClass$IInvocable.getDescriptor(IClass.java:865)\n\tat org.codehaus.janino.IClass.getIMethods(IClass.java:211)\n\tat org.codehaus.janino.IClass.getIMethods(IClass.java:200)\n\tat org.codehaus.janino.UnitCompiler.compile2(UnitCompiler.java:439)\n\tat org.codehaus.janino.UnitCompiler.compile2(UnitCompiler.java:420)\n\tat org.codehaus.janino.UnitCompiler.access$400(UnitCompiler.java:206)\n\tat org.codehaus.janino.UnitCompiler$2.visitPackageMemberClassDeclaration(UnitCompiler.java:374)\n\tat org.codehaus.janino.UnitCompiler$2.visitPackageMemberClassDeclaration(UnitCompiler.java:369)\n\tat org.codehaus.janino.Java$AbstractPackageMemberClassDeclaration.accept(Java.java:1309)\n\tat org.codehaus.janino.UnitCompiler.compile(UnitCompiler.java:369)\n\tat org.codehaus.janino.UnitCompiler.compileUnit(UnitCompiler.java:345)\n\tat org.codehaus.janino.SimpleCompiler.compileToClassLoader(SimpleCompiler.java:396)\n\tat org.codehaus.janino.ClassBodyEvaluator.compileToClass(ClassBodyEvaluator.java:311)\n\tat org.codehaus.janino.ClassBodyEvaluator.cook(ClassBodyEvaluator.java:229)\n\tat org.codehaus.janino.SimpleCompiler.cook(SimpleCompiler.java:196)\n\tat org.codehaus.commons.compiler.Cookable.cook(Cookable.java:91)\n\tat org.apache.spark.sql.catalyst.expressions.codegen.CodeGenerator$.org$apache$spark$sql$catalyst$expressions$codegen$CodeGenerator$$doCompile(CodeGenerator.scala:935)\n\tat org.apache.spark.sql.catalyst.expressions.codegen.CodeGenerator$$anon$1.load(CodeGenerator.scala:998)\n\tat org.apache.spark.sql.catalyst.expressions.codegen.CodeGenerator$$anon$1.load(CodeGenerator.scala:995)\n\tat org.spark_project.guava.cache.LocalCache$LoadingValueReference.loadFuture(LocalCache.java:3599)\n\tat org.spark_project.guava.cache.LocalCache$Segment.loadSync(LocalCache.java:2379)\n\tat org.spark_project.guava.cache.LocalCache$Segment.lockedGetOrLoad(LocalCache.java:2342)\n\tat org.spark_project.guava.cache.LocalCache$Segment.get(LocalCache.java:2257)\n\tat org.spark_project.guava.cache.LocalCache.get(LocalCache.java:4000)\n\tat org.spark_project.guava.cache.LocalCache.getOrLoad(LocalCache.java:4004)\n\tat org.spark_project.guava.cache.LocalCache$LocalLoadingCache.get(LocalCache.java:4874)\n\tat org.apache.spark.sql.catalyst.expressions.codegen.CodeGenerator$.compile(CodeGenerator.scala:890)\n\tat org.apache.spark.sql.catalyst.expressions.codegen.GenerateOrdering$.create(GenerateOrdering.scala:155)\n\tat org.apache.spark.sql.catalyst.expressions.codegen.GenerateOrdering$.create(GenerateOrdering.scala:43)\n\tat org.apache.spark.sql.catalyst.expressions.codegen.CodeGenerator.generate(CodeGenerator.scala:874)\n\tat org.apache.spark.sql.catalyst.expressions.codegen.LazilyGeneratedOrdering.\u003cinit\u003e(GenerateOrdering.scala:169)\n\tat org.apache.spark.sql.catalyst.expressions.codegen.LazilyGeneratedOrdering.\u003cinit\u003e(GenerateOrdering.scala:166)\n\tat org.apache.spark.sql.execution.TakeOrderedAndProjectExec.executeCollect(limit.scala:132)\n\tat org.apache.spark.sql.Dataset$$anonfun$org$apache$spark$sql$Dataset$$execute$1$1.apply(Dataset.scala:2371)\n\tat org.apache.spark.sql.execution.SQLExecution$.withNewExecutionId(SQLExecution.scala:57)\n\tat org.apache.spark.sql.Dataset.withNewExecutionId(Dataset.scala:2765)\n\tat org.apache.spark.sql.Dataset.org$apache$spark$sql$Dataset$$execute$1(Dataset.scala:2370)\n\tat org.apache.spark.sql.Dataset.org$apache$spark$sql$Dataset$$collect(Dataset.scala:2377)\n\tat org.apache.spark.sql.Dataset$$anonfun$head$1.apply(Dataset.scala:2113)\n\tat org.apache.spark.sql.Dataset$$anonfun$head$1.apply(Dataset.scala:2112)\n\tat org.apache.spark.sql.Dataset.withTypedCallback(Dataset.scala:2795)\n\tat org.apache.spark.sql.Dataset.head(Dataset.scala:2112)\n\tat org.apache.spark.sql.Dataset.take(Dataset.scala:2327)\n\tat sun.reflect.NativeMethodAccessorImpl.invoke0(Native Method)\n\tat sun.reflect.NativeMethodAccessorImpl.invoke(NativeMethodAccessorImpl.java:62)\n\tat sun.reflect.DelegatingMethodAccessorImpl.invoke(DelegatingMethodAccessorImpl.java:43)\n\tat java.lang.reflect.Method.invoke(Method.java:498)\n\tat org.apache.zeppelin.spark.ZeppelinContext.showDF(ZeppelinContext.java:235)\n\tat org.apache.zeppelin.spark.SparkSqlInterpreter.interpret(SparkSqlInterpreter.java:130)\n\tat org.apache.zeppelin.interpreter.LazyOpenInterpreter.interpret(LazyOpenInterpreter.java:97)\n\tat org.apache.zeppelin.interpreter.remote.RemoteInterpreterServer$InterpretJob.jobRun(RemoteInterpreterServer.java:498)\n\tat org.apache.zeppelin.scheduler.Job.run(Job.java:175)\n\tat org.apache.zeppelin.scheduler.FIFOScheduler$1.run(FIFOScheduler.java:139)\n\tat java.util.concurrent.Executors$RunnableAdapter.call(Executors.java:511)\n\tat java.util.concurrent.FutureTask.run(FutureTask.java:266)\n\tat java.util.concurrent.ScheduledThreadPoolExecutor$ScheduledFutureTask.access$201(ScheduledThreadPoolExecutor.java:180)\n\tat java.util.concurrent.ScheduledThreadPoolExecutor$ScheduledFutureTask.run(ScheduledThreadPoolExecutor.java:293)\n\tat java.util.concurrent.ThreadPoolExecutor.runWorker(ThreadPoolExecutor.java:1142)\n\tat java.util.concurrent.ThreadPoolExecutor$Worker.run(ThreadPoolExecutor.java:617)\n\tat java.lang.Thread.run(Thread.java:748)\n"
          }
        ]
      },
      "apps": [],
      "jobName": "paragraph_1505352192045_-369620934",
      "id": "20170914-012312_1115162763",
      "dateCreated": "Sep 14, 2017 1:23:12 AM",
      "dateStarted": "Sep 14, 2017 4:51:06 PM",
      "dateFinished": "Sep 14, 2017 4:51:06 PM",
      "status": "ERROR",
      "progressUpdateIntervalMs": 500
    },
    {
      "text": "%spark\nssc.stop()\n",
      "user": "anonymous",
      "dateUpdated": "Sep 14, 2017 4:51:14 PM",
      "config": {
        "colWidth": 12.0,
        "enabled": true,
        "results": {},
        "editorSetting": {
          "language": "text",
          "editOnDblClick": false
        },
        "editorMode": "ace/mode/text"
      },
      "settings": {
        "params": {},
        "forms": {}
      },
      "results": {
        "code": "SUCCESS",
        "msg": []
      },
      "apps": [],
      "jobName": "paragraph_1505352203483_1212866617",
      "id": "20170914-012323_2060953373",
      "dateCreated": "Sep 14, 2017 1:23:23 AM",
      "dateStarted": "Sep 14, 2017 4:51:14 PM",
      "dateFinished": "Sep 14, 2017 4:51:17 PM",
      "status": "FINISHED",
      "progressUpdateIntervalMs": 500
    },
    {
      "text": "%spark\n",
      "user": "anonymous",
      "dateUpdated": "Sep 14, 2017 1:31:34 AM",
      "config": {},
      "settings": {
        "params": {},
        "forms": {}
      },
      "apps": [],
      "jobName": "paragraph_1505352694271_-1518878825",
      "id": "20170914-013134_140870628",
      "dateCreated": "Sep 14, 2017 1:31:34 AM",
      "status": "READY",
      "errorMessage": "",
      "progressUpdateIntervalMs": 500
    }
  ],
  "name": "Bayes Lecture (Part 1.4 User Defined Function)",
  "id": "2CSN2RCK2",
  "angularObjects": {
    "2CTVVVTV3:shared_process": [],
    "2CTRT8FA3:shared_process": [],
    "2CVAURWQU:shared_process": [],
    "2CUQ18ZYF:shared_process": [],
    "2CVBQ7MEQ:shared_process": [],
    "2CV1KAATZ:shared_process": [],
    "2CU6JXGC3:shared_process": [],
    "2CS2Y94EQ:shared_process": [],
    "2CS1V8HFJ:shared_process": [],
    "2CV71473K:shared_process": [],
    "2CVCE1ANQ:shared_process": [],
    "2CT9VNU2V:shared_process": [],
    "2CUA39CTW:shared_process": [],
    "2CVENK4UN:shared_process": [],
    "2CTRSKG8X:shared_process": [],
    "2CT49XVEY:shared_process": [],
    "2CUM9FYYM:shared_process": [],
    "2CUSNPA9P:shared_process": [],
    "2CU76UQWX:shared_process": []
  },
  "config": {},
  "info": {}
}